{
  "implements": "utam-salesforceapp/pageObjects/authentication/eula",
  "platform": "native",
  "profile": [
    {
      "platform": "android_phone"
    }
  ],
  "root": true,
  "selector": {
    "uiautomator": "resourceId(\"android:id/action_bar\")"
  },
  "methods": [
    {
      "name": "accept",
      "compose": [
        {
          "element": "iaccept",
          "apply": "click"
        }
      ]
    }
  ],
  "elements": [
    {
      "type": [
        "clickable"
      ],
      "name": "iaccept",
      "selector": {
        "uiautomator": "resourceId(\"com.salesforce.chatter:id/mi_accept\")"
      }
    }
  ]
}
